README.md
setup.py
puzzles/__init__.py
puzzles/logger.py
puzzles/models.py
puzzles/utils.py
puzzles/version.py
puzzles.egg-info/PKG-INFO
puzzles.egg-info/SOURCES.txt
puzzles.egg-info/dependency_links.txt
puzzles.egg-info/not-zip-safe
puzzles.egg-info/requires.txt
puzzles.egg-info/top_level.txt