Metadata-Version: 2.1
Name: puzzles
Version: 0.0.12
Summary: solve puzzles with Python
Home-page: https://github.com/vsoch/puzzles
Author: Vanessa Sochat
Author-email: vsoch@users.noreply.github.com
Maintainer: Vanessa Sochat
Maintainer-email: vsoch@users.noreply.github.com
License: LICENSE
Keywords: python puzzle solver
Platform: UNKNOWN
Classifier: Intended Audience :: Science/Research
Classifier: Intended Audience :: Developers
Classifier: License :: OSI Approved :: GNU Affero General Public License v3 or later (AGPLv3+)
Classifier: Programming Language :: C
Classifier: Programming Language :: Python
Classifier: Topic :: Software Development
Classifier: Topic :: Scientific/Engineering
Classifier: Operating System :: Unix
Classifier: Programming Language :: Python :: 3
